xdotool/__init__.py
xdotool-0.3.0.dist-info/METADATA
xdotool-0.3.0.dist-info/WHEEL
xdotool-0.3.0.dist-info/RECORD
