Metadata-Version: 2.1
Name: xdotool
Version: 0.3.0
Summary: 
Home-page: https://github.com/Tlaloc-Es/xdotool
License: MIT
Keywords: pxdotool
Author: Tlaloc-Es
Author-email: dev@tlaloc-es.com
Requires-Python: >=3.10,<4.0
Classifier: License :: OSI Approved :: MIT License
Classifier: Programming Language :: Python :: 3
Classifier: Programming Language :: Python :: 3.10
Classifier: Programming Language :: Python :: 3.11
Project-URL: Repository, https://github.com/Tlaloc-Es/xdotool
